amamiyass/AdjGraph.py
amamiyass/BF.py
amamiyass/BFS1.py
amamiyass/BFS2.py
amamiyass/BTree.py
amamiyass/CDLinkList.py
amamiyass/CLinkList.py
amamiyass/CSqQueue.py
amamiyass/CreateBTree1.py
amamiyass/CreateBTree2.py
amamiyass/DFS1.py
amamiyass/DFS2.py
amamiyass/DLinkList.py
amamiyass/Dijkstra.py
amamiyass/Floyd.py
amamiyass/Huffman.py
amamiyass/KMP.py
amamiyass/KMPval.py
amamiyass/Kruskal.py
amamiyass/LinkList.py
amamiyass/LinkQueue.py
amamiyass/LinkStack.py
amamiyass/LinkString.py
amamiyass/MatGraph.py
amamiyass/Prim.py
amamiyass/SqList.py
amamiyass/SqQueue.py
amamiyass/SqStack.py
amamiyass/SqString.py
amamiyass/ThreadBTree.py
amamiyass/TopSort.py
amamiyass/Tup.py
amamiyass/binaryTree.py
amamiyass/tmp.py
amamiyass/tmp1.py
amamiyass-1.0.dist-info/LICENSE
amamiyass-1.0.dist-info/METADATA
amamiyass-1.0.dist-info/WHEEL
amamiyass-1.0.dist-info/top_level.txt
amamiyass-1.0.dist-info/RECORD
