Metadata-Version: 2.1
Name: amamiyass
Version: 1.0
Summary: This is a pacage, writen by renyumeng
Home-page: https://github.com/renyumeng1
Author: renyumeng
Author-email: 235328756@qq.com
License: MIT
Platform: UNKNOWN
License-File: LICENSE
